{
    "os": "Linux-5.8.0-53-generic-x86_64-with-debian-bullseye-sid",
    "python": "3.7.9",
    "heartbeatAt": "2021-05-27T15:20:43.843009",
    "startedAt": "2021-05-27T15:20:42.782491",
    "docker": null,
    "gpu": "GeForce RTX 2070 SUPER",
    "gpu_count": 1,
    "cpu_count": 12,
    "cuda": null,
    "args": [
        "--node-ip-address=192.168.0.22",
        "--node-manager-port=37999",
        "--object-store-name=/tmp/ray/session_2021-05-28_00-19-54_847898_279124/sockets/plasma_store",
        "--raylet-name=/tmp/ray/session_2021-05-28_00-19-54_847898_279124/sockets/raylet",
        "--redis-address=192.168.0.22:31269",
        "--temp-dir=/tmp/ray",
        "--metrics-agent-port=62829",
        "--logging-rotate-bytes=536870912",
        "--logging-rotate-backup-count=5",
        "--redis-password=5241590000000000"
    ],
    "state": "running",
    "program": "<python with no main file>",
    "git": {
        "remote": "https://github.com/neverparadise/MineRL_Distributed-Imitation-Learning.git",
        "commit": "94b640c9362a325631526cbd94330d4e642190b7"
    },
    "email": "ye20013@gmail.com",
    "root": "/home/kukjin/Study/RL/softwardcapstonedesign/ApexDQFD",
    "host": "kukjin-System-Product-Name",
    "username": "kukjin",
    "executable": "/home/kukjin/anaconda3/envs/minerl/bin/python"
}
